[
    {
        "id": "hedensbyn",
        "name": "Hedensbyns Företagspark",
        "mainDescription": {
            "id": 1,
            "heading": "Hedensbyns Företagspark",
            "text": "<p>Skellefteå Kommun är i full gång att skapa en nya företagspark på Hedensbyn. Under andra halvåret 2018 kommer Northvolt att ta det första spadtaget i arbetet med att skapa Europas största  produktionsanläggning för litiumjonbatterier i samma område.</p><p>Satsningen väntas skapa 2 000 till 2 500 nya arbetstillfällen och skapa många nya affärsmöjligheter för underleverantörer.</p><p>För att bidra till utvecklingen planerar vi att uppföra ett industriradhus  med  21 stycken enheter. </p><p>Kontakta oss gärna om ni har planer på att etablera er i området. Vi har goda möjligheter att hjälpa er med funktionella och prisvärda lokallösningar.</p>",
            "size": 1
        },
        "descriptions": [
            {
                "id": 6,
                "heading": "Vad är industriradhus?",
                "text": "Industriradhus är en ny typ av lösning för små och medelstora företag som vill äga sina egna lokaler men som på egen hand inte vill investera i uppförandet av en större industribyggnad. Istället kan ett kluster av mindre företag gå samman och bygga en större lokal med enheter som upplåts som bostadsrätter. Det skapas även gemensamma ytor såsom lunchrum, gym, konferensrum etc",
                "size": 3
            },
            {
                "id": 7,
                "heading": "Två typer av enheter",
                "text": "På Hedensbyns företagspark kommer det gå att beställa två olika typer av industriradhus. En mindre modell som lämpar sig som garage eller verkstad och en större modell som riktar sig till dig som vill ha en butikslokal med tillhörande lager/kontor. Alternativt kombinera ihop både en butiksyta med ett garage eller lagerlokal i anslutning till butiken. Möjligheterna är många, bara att bestämma vilken kombination man vill ha.",
                "size": 3
            }
        ],
        "pictures": [
            {
                "id": 2,
                "fileName": "hedensbyn1.png"
            },
            {
                "id": 3,
                "fileName": "hedensbyn2.png"
            }
        ],
        "units": [
            {
                "id": "hfp01",
                "projectId": "hedensbyn",
                "salesAgent": {
                    "id": "1989fb0b-15c0-4034-9e1c-2b8004e6e1c0",
                    "name": "Jörgen Munter",
                    "email": "jorgen.munter@industriradhus.se",
                    "phone": "070-173 37 88",
                    "picture": {
                        "fileName": "jorgen.png"
                    }
                },
                "name": "Standardenhet (HFP01)",
                "mainDescription": {
                    "id": "1001",
                    "heading": "Standardenhet",
                    "text": "HFP01",
                    "size": 1
                },
                "descriptions": null,
                "characteristicsSections": [
                    {
                        "heading": "Byggnadsbeskrivning",
                        "characteristics": [
                            {
                                "heading": "Grund",
                                "text": "Isolerad betongplatta"
                            },
                            {
                                "heading": "Fasad",
                                "text": "Plåt"
                            },
                            {
                                "heading": "Stomme",
                                "text": "Stål"
                            },
                            {
                                "heading": "Yttertak",
                                "text": "Takpapp"
                            },
                            {
                                "heading": "Innertak",
                                "text": "Takplåt"
                            },
                            {
                                "heading": "Fönster",
                                "text": "3-glas"
                            },
                            {
                                "heading": "Garageport",
                                "text": "4x4,5 m"
                            },
                            {
                                "heading": "Dörr",
                                "text": "Ståldörr typ Daloc"
                            },
                            {
                                "heading": "Trappor",
                                "text": "Spiraltrappa i stål"
                            }
                        ]
                    },
                    {
                        "heading": "Installationer",
                        "characteristics": [
                            {
                                "heading": "VVS",
                                "text": "Fastigheten ansluts till kommunala nätet"
                            },
                            {
                                "heading": "Uppvärmning",
                                "text": "Frånluftvärmepump med golvvärme"
                            },
                            {
                                "heading": "TV/Tele/Bredband",
                                "text": "Fastigheten är förberedd för att anslutas till fibernät"
                            },
                            {
                                "heading": "Ventilation",
                                "text": "Mekanisk till- och frånluftsvent. Varje enskild bostadsrättshavare svarar för att ventilationen är dimensionerad efter sin verksamhet"
                            }
                        ]
                    }
                ],
                "pictures": [
                    {
                        "fileName": "hfp01-01.png"
                    },
                    {
                        "fileName": "hfp01-02.png"
                    }
                ],
                "thumbnail": "standardenhet.png",
                "googleMapsUrl": "https://www.google.com/maps/embed?pb=!1m18!1m12!1m3!1d1702.582084811809!2d21.02675231660073!3d64.7415872728741!2m3!1f0!2f0!3f0!3m2!1i1024!2i768!4f13.1!3m3!1m2!1s0x0%3A0x0!2zNjTCsDQ0JzI5LjciTiAyMcKwMDEnNDQuMiJF!5e0!3m2!1ssv!2sse!4v1527750055465",
                "size": 144,
                "price": 1229000,
                "rent": 4360,
                "sold": false
            },
            {
                "id": "hfp02",
                "projectId": "hedensbyn",
                "salesAgent": {
                    "id": "1989fb0b-15c0-4034-9e1c-2b8004e6e1c0",
                    "name": "Jörgen Munter",
                    "email": "jorgen.munter@industriradhus.se",
                    "phone": "070-173 37 88",
                    "picture": {
                        "fileName": "jorgen.png"
                    }
                },
                "name": "Standardenhet (HFP02)",
                "mainDescription": {
                    "id": "1002",
                    "heading": "Standardenhet",
                    "text": "HFP02",
                    "size": 1
                },
                "descriptions": null,
                "characteristicsSections": [
                    {
                        "heading": "Byggnadsbeskrivning",
                        "characteristics": [
                            {
                                "heading": "Grund",
                                "text": "Isolerad betongplatta"
                            },
                            {
                                "heading": "Fasad",
                                "text": "Plåt"
                            },
                            {
                                "heading": "Stomme",
                                "text": "Stål"
                            },
                            {
                                "heading": "Yttertak",
                                "text": "Takpapp"
                            },
                            {
                                "heading": "Innertak",
                                "text": "Takplåt"
                            },
                            {
                                "heading": "Fönster",
                                "text": "3-glas"
                            },
                            {
                                "heading": "Garageport",
                                "text": "4x4,5 m"
                            },
                            {
                                "heading": "Dörr",
                                "text": "Ståldörr typ Daloc"
                            },
                            {
                                "heading": "Trappor",
                                "text": "Spiraltrappa i stål"
                            }
                        ]
                    },
                    {
                        "heading": "Installationer",
                        "characteristics": [
                            {
                                "heading": "VVS",
                                "text": "Fastigheten ansluts till kommunala nätet"
                            },
                            {
                                "heading": "Uppvärmning",
                                "text": "Frånluftvärmepump med golvvärme"
                            },
                            {
                                "heading": "TV/Tele/Bredband",
                                "text": "Fastigheten är förberedd för att anslutas till fibernät"
                            },
                            {
                                "heading": "Ventilation",
                                "text": "Mekanisk till- och frånluftsvent. Varje enskild bostadsrättshavare svarar för att ventilationen är dimensionerad efter sin verksamhet"
                            }
                        ]
                    }
                ],
                "pictures": [
                    {
                        "fileName": "hfp02-01.png"
                    },
                    {
                        "fileName": "hfp02-02.png"
                    }
                ],
                "thumbnail": "standardenhet.png",
                "googleMapsUrl": "https://www.google.com/maps/embed?pb=!1m18!1m12!1m3!1d1702.582084811809!2d21.02675231660073!3d64.7415872728741!2m3!1f0!2f0!3f0!3m2!1i1024!2i768!4f13.1!3m3!1m2!1s0x0%3A0x0!2zNjTCsDQ0JzI5LjciTiAyMcKwMDEnNDQuMiJF!5e0!3m2!1ssv!2sse!4v1527750055465",
                "size": 144,
                "price": 1229000,
                "rent": 4360,
                "sold": false
            },
            {
                "id": "hfp03",
                "projectId": "hedensbyn",
                "salesAgent": {
                    "id": "1989fb0b-15c0-4034-9e1c-2b8004e6e1c0",
                    "name": "Jörgen Munter",
                    "email": "jorgen.munter@industriradhus.se",
                    "phone": "070-173 37 88",
                    "picture": {
                        "fileName": "jorgen.png"
                    }
                },
                "name": "Standardenhet (HFP03)",
                "mainDescription": {
                    "id": "1003",
                    "heading": "Standardenhet",
                    "text": "HFP03",
                    "size": 1
                },
                "descriptions": null,
                "characteristicsSections": [
                    {
                        "heading": "Byggnadsbeskrivning",
                        "characteristics": [
                            {
                                "heading": "Grund",
                                "text": "Isolerad betongplatta"
                            },
                            {
                                "heading": "Fasad",
                                "text": "Plåt"
                            },
                            {
                                "heading": "Stomme",
                                "text": "Stål"
                            },
                            {
                                "heading": "Yttertak",
                                "text": "Takpapp"
                            },
                            {
                                "heading": "Innertak",
                                "text": "Takplåt"
                            },
                            {
                                "heading": "Fönster",
                                "text": "3-glas"
                            },
                            {
                                "heading": "Garageport",
                                "text": "4x4,5 m"
                            },
                            {
                                "heading": "Dörr",
                                "text": "Ståldörr typ Daloc"
                            },
                            {
                                "heading": "Trappor",
                                "text": "Spiraltrappa i stål"
                            }
                        ]
                    },
                    {
                        "heading": "Installationer",
                        "characteristics": [
                            {
                                "heading": "VVS",
                                "text": "Fastigheten ansluts till kommunala nätet"
                            },
                            {
                                "heading": "Uppvärmning",
                                "text": "Frånluftvärmepump med golvvärme"
                            },
                            {
                                "heading": "TV/Tele/Bredband",
                                "text": "Fastigheten är förberedd för att anslutas till fibernät"
                            },
                            {
                                "heading": "Ventilation",
                                "text": "Mekanisk till- och frånluftsvent. Varje enskild bostadsrättshavare svarar för att ventilationen är dimensionerad efter sin verksamhet"
                            }
                        ]
                    }
                ],
                "pictures": [
                    {
                        "fileName": "hfp03-01.png"
                    },
                    {
                        "fileName": "hfp03-02.png"
                    }
                ],
                "thumbnail": "standardenhet.png",
                "googleMapsUrl": "https://www.google.com/maps/embed?pb=!1m18!1m12!1m3!1d1702.582084811809!2d21.02675231660073!3d64.7415872728741!2m3!1f0!2f0!3f0!3m2!1i1024!2i768!4f13.1!3m3!1m2!1s0x0%3A0x0!2zNjTCsDQ0JzI5LjciTiAyMcKwMDEnNDQuMiJF!5e0!3m2!1ssv!2sse!4v1527750055465",
                "size": 144,
                "price": 1229000,
                "rent": 4360,
                "sold": false
            },
            {
                "id": "hfp04",
                "projectId": "hedensbyn",
                "salesAgent": {
                    "id": "1989fb0b-15c0-4034-9e1c-2b8004e6e1c0",
                    "name": "Jörgen Munter",
                    "email": "jorgen.munter@industriradhus.se",
                    "phone": "070-173 37 88",
                    "picture": {
                        "fileName": "jorgen.png"
                    }
                },
                "name": "Standardenhet (HFP04)",
                "mainDescription": {
                    "id": "1004",
                    "heading": "Standardenhet",
                    "text": "HFP04",
                    "size": 1
                },
                "descriptions": null,
                "characteristicsSections": [
                    {
                        "heading": "Byggnadsbeskrivning",
                        "characteristics": [
                            {
                                "heading": "Grund",
                                "text": "Isolerad betongplatta"
                            },
                            {
                                "heading": "Fasad",
                                "text": "Plåt"
                            },
                            {
                                "heading": "Stomme",
                                "text": "Stål"
                            },
                            {
                                "heading": "Yttertak",
                                "text": "Takpapp"
                            },
                            {
                                "heading": "Innertak",
                                "text": "Takplåt"
                            },
                            {
                                "heading": "Fönster",
                                "text": "3-glas"
                            },
                            {
                                "heading": "Garageport",
                                "text": "4x4,5 m"
                            },
                            {
                                "heading": "Dörr",
                                "text": "Ståldörr typ Daloc"
                            },
                            {
                                "heading": "Trappor",
                                "text": "Spiraltrappa i stål"
                            }
                        ]
                    },
                    {
                        "heading": "Installationer",
                        "characteristics": [
                            {
                                "heading": "VVS",
                                "text": "Fastigheten ansluts till kommunala nätet"
                            },
                            {
                                "heading": "Uppvärmning",
                                "text": "Frånluftvärmepump med golvvärme"
                            },
                            {
                                "heading": "TV/Tele/Bredband",
                                "text": "Fastigheten är förberedd för att anslutas till fibernät"
                            },
                            {
                                "heading": "Ventilation",
                                "text": "Mekanisk till- och frånluftsvent. Varje enskild bostadsrättshavare svarar för att ventilationen är dimensionerad efter sin verksamhet"
                            }
                        ]
                    }
                ],
                "pictures": [
                    {
                        "fileName": "hfp04-01.png"
                    },
                    {
                        "fileName": "hfp04-02.png"
                    }
                ],
                "thumbnail": "standardenhet.png",
                "googleMapsUrl": "https://www.google.com/maps/embed?pb=!1m18!1m12!1m3!1d1702.582084811809!2d21.02675231660073!3d64.7415872728741!2m3!1f0!2f0!3f0!3m2!1i1024!2i768!4f13.1!3m3!1m2!1s0x0%3A0x0!2zNjTCsDQ0JzI5LjciTiAyMcKwMDEnNDQuMiJF!5e0!3m2!1ssv!2sse!4v1527750055465",
                "size": 144,
                "price": 1229000,
                "rent": 4360,
                "sold": false
            },
            {
                "id": "hfp05",
                "projectId": "hedensbyn",
                "salesAgent": {
                    "id": "1989fb0b-15c0-4034-9e1c-2b8004e6e1c0",
                    "name": "Jörgen Munter",
                    "email": "jorgen.munter@industriradhus.se",
                    "phone": "070-173 37 88",
                    "picture": {
                        "fileName": "jorgen.png"
                    }
                },
                "name": "Standardenhet (HFP05)",
                "mainDescription": {
                    "id": "1004",
                    "heading": "Standardenhet",
                    "text": "HFP05",
                    "size": 1
                },
                "descriptions": null,
                "characteristicsSections": [
                    {
                        "heading": "Byggnadsbeskrivning",
                        "characteristics": [
                            {
                                "heading": "Grund",
                                "text": "Isolerad betongplatta"
                            },
                            {
                                "heading": "Fasad",
                                "text": "Plåt"
                            },
                            {
                                "heading": "Stomme",
                                "text": "Stål"
                            },
                            {
                                "heading": "Yttertak",
                                "text": "Takpapp"
                            },
                            {
                                "heading": "Innertak",
                                "text": "Takplåt"
                            },
                            {
                                "heading": "Fönster",
                                "text": "3-glas"
                            },
                            {
                                "heading": "Garageport",
                                "text": "4x4,5 m"
                            },
                            {
                                "heading": "Dörr",
                                "text": "Ståldörr typ Daloc"
                            },
                            {
                                "heading": "Trappor",
                                "text": "Spiraltrappa i stål"
                            }
                        ]
                    },
                    {
                        "heading": "Installationer",
                        "characteristics": [
                            {
                                "heading": "VVS",
                                "text": "Fastigheten ansluts till kommunala nätet"
                            },
                            {
                                "heading": "Uppvärmning",
                                "text": "Frånluftvärmepump med golvvärme"
                            },
                            {
                                "heading": "TV/Tele/Bredband",
                                "text": "Fastigheten är förberedd för att anslutas till fibernät"
                            },
                            {
                                "heading": "Ventilation",
                                "text": "Mekanisk till- och frånluftsvent. Varje enskild bostadsrättshavare svarar för att ventilationen är dimensionerad efter sin verksamhet"
                            }
                        ]
                    }
                ],
                "pictures": [
                    {
                        "fileName": "hfp05-01.png"
                    },
                    {
                        "fileName": "hfp05-02.png"
                    }
                ],
                "thumbnail": "standardenhet.png",
                "googleMapsUrl": "https://www.google.com/maps/embed?pb=!1m18!1m12!1m3!1d1702.582084811809!2d21.02675231660073!3d64.7415872728741!2m3!1f0!2f0!3f0!3m2!1i1024!2i768!4f13.1!3m3!1m2!1s0x0%3A0x0!2zNjTCsDQ0JzI5LjciTiAyMcKwMDEnNDQuMiJF!5e0!3m2!1ssv!2sse!4v1527750055465",
                "size": 144,
                "price": 1229000,
                "rent": 4360,
                "sold": false
            },
            {
                "id": "hfp06",
                "projectId": "hedensbyn",
                "salesAgent": {
                    "id": "1989fb0b-15c0-4034-9e1c-2b8004e6e1c0",
                    "name": "Jörgen Munter",
                    "email": "jorgen.munter@industriradhus.se",
                    "phone": "070-173 37 88",
                    "picture": {
                        "fileName": "jorgen.png"
                    }
                },
                "name": "Standardenhet (HFP06)",
                "mainDescription": {
                    "id": "1006",
                    "heading": "Standardenhet",
                    "text": "HFP06",
                    "size": 1
                },
                "descriptions": null,
                "characteristicsSections": [
                    {
                        "heading": "Byggnadsbeskrivning",
                        "characteristics": [
                            {
                                "heading": "Grund",
                                "text": "Isolerad betongplatta"
                            },
                            {
                                "heading": "Fasad",
                                "text": "Plåt"
                            },
                            {
                                "heading": "Stomme",
                                "text": "Stål"
                            },
                            {
                                "heading": "Yttertak",
                                "text": "Takpapp"
                            },
                            {
                                "heading": "Innertak",
                                "text": "Takplåt"
                            },
                            {
                                "heading": "Fönster",
                                "text": "3-glas"
                            },
                            {
                                "heading": "Garageport",
                                "text": "4x4,5 m"
                            },
                            {
                                "heading": "Dörr",
                                "text": "Ståldörr typ Daloc"
                            },
                            {
                                "heading": "Trappor",
                                "text": "Spiraltrappa i stål"
                            }
                        ]
                    },
                    {
                        "heading": "Installationer",
                        "characteristics": [
                            {
                                "heading": "VVS",
                                "text": "Fastigheten ansluts till kommunala nätet"
                            },
                            {
                                "heading": "Uppvärmning",
                                "text": "Frånluftvärmepump med golvvärme"
                            },
                            {
                                "heading": "TV/Tele/Bredband",
                                "text": "Fastigheten är förberedd för att anslutas till fibernät"
                            },
                            {
                                "heading": "Ventilation",
                                "text": "Mekanisk till- och frånluftsvent. Varje enskild bostadsrättshavare svarar för att ventilationen är dimensionerad efter sin verksamhet"
                            }
                        ]
                    }
                ],
                "pictures": [
                    {
                        "fileName": "hfp06-01.png"
                    },
                    {
                        "fileName": "hfp06-02.png"
                    }
                ],
                "thumbnail": "standardenhet.png",
                "googleMapsUrl": "https://www.google.com/maps/embed?pb=!1m18!1m12!1m3!1d1702.582084811809!2d21.02675231660073!3d64.7415872728741!2m3!1f0!2f0!3f0!3m2!1i1024!2i768!4f13.1!3m3!1m2!1s0x0%3A0x0!2zNjTCsDQ0JzI5LjciTiAyMcKwMDEnNDQuMiJF!5e0!3m2!1ssv!2sse!4v1527750055465",
                "size": 144,
                "price": 1229000,
                "rent": 4360,
                "sold": false
            },
            {
                "id": "hfp07",
                "projectId": "hedensbyn",
                "salesAgent": {
                    "id": "1989fb0b-15c0-4034-9e1c-2b8004e6e1c0",
                    "name": "Jörgen Munter",
                    "email": "jorgen.munter@industriradhus.se",
                    "phone": "070-173 37 88",
                    "picture": {
                        "fileName": "jorgen.png"
                    }
                },
                "name": "Standardenhet (HFP07)",
                "mainDescription": {
                    "id": "1007",
                    "heading": "Standardenhet",
                    "text": "HFP07",
                    "size": 1
                },
                "descriptions": null,
                "characteristicsSections": [
                    {
                        "heading": "Byggnadsbeskrivning",
                        "characteristics": [
                            {
                                "heading": "Grund",
                                "text": "Isolerad betongplatta"
                            },
                            {
                                "heading": "Fasad",
                                "text": "Plåt"
                            },
                            {
                                "heading": "Stomme",
                                "text": "Stål"
                            },
                            {
                                "heading": "Yttertak",
                                "text": "Takpapp"
                            },
                            {
                                "heading": "Innertak",
                                "text": "Takplåt"
                            },
                            {
                                "heading": "Fönster",
                                "text": "3-glas"
                            },
                            {
                                "heading": "Garageport",
                                "text": "4x4,5 m"
                            },
                            {
                                "heading": "Dörr",
                                "text": "Ståldörr typ Daloc"
                            },
                            {
                                "heading": "Trappor",
                                "text": "Spiraltrappa i stål"
                            }
                        ]
                    },
                    {
                        "heading": "Installationer",
                        "characteristics": [
                            {
                                "heading": "VVS",
                                "text": "Fastigheten ansluts till kommunala nätet"
                            },
                            {
                                "heading": "Uppvärmning",
                                "text": "Frånluftvärmepump med golvvärme"
                            },
                            {
                                "heading": "TV/Tele/Bredband",
                                "text": "Fastigheten är förberedd för att anslutas till fibernät"
                            },
                            {
                                "heading": "Ventilation",
                                "text": "Mekanisk till- och frånluftsvent. Varje enskild bostadsrättshavare svarar för att ventilationen är dimensionerad efter sin verksamhet"
                            }
                        ]
                    }
                ],
                "pictures": [
                    {
                        "fileName": "hfp07-01.png"
                    },
                    {
                        "fileName": "hfp07-02.png"
                    }
                ],
                "thumbnail": "standardenhet.png",
                "googleMapsUrl": "https://www.google.com/maps/embed?pb=!1m18!1m12!1m3!1d1702.582084811809!2d21.02675231660073!3d64.7415872728741!2m3!1f0!2f0!3f0!3m2!1i1024!2i768!4f13.1!3m3!1m2!1s0x0%3A0x0!2zNjTCsDQ0JzI5LjciTiAyMcKwMDEnNDQuMiJF!5e0!3m2!1ssv!2sse!4v1527750055465",
                "size": 144,
                "price": 1229000,
                "rent": 4360,
                "sold": false
            },
            {
                "id": "hfp08",
                "projectId": "hedensbyn",
                "salesAgent": {
                    "id": "1989fb0b-15c0-4034-9e1c-2b8004e6e1c0",
                    "name": "Jörgen Munter",
                    "email": "jorgen.munter@industriradhus.se",
                    "phone": "070-173 37 88",
                    "picture": {
                        "fileName": "jorgen.png"
                    }
                },
                "name": "Standardenhet (HFP08)",
                "mainDescription": {
                    "id": "1008",
                    "heading": "Standardenhet",
                    "text": "HFP08",
                    "size": 1
                },
                "descriptions": null,
                "characteristicsSections": [
                    {
                        "heading": "Byggnadsbeskrivning",
                        "characteristics": [
                            {
                                "heading": "Grund",
                                "text": "Isolerad betongplatta"
                            },
                            {
                                "heading": "Fasad",
                                "text": "Plåt"
                            },
                            {
                                "heading": "Stomme",
                                "text": "Stål"
                            },
                            {
                                "heading": "Yttertak",
                                "text": "Takpapp"
                            },
                            {
                                "heading": "Innertak",
                                "text": "Takplåt"
                            },
                            {
                                "heading": "Fönster",
                                "text": "3-glas"
                            },
                            {
                                "heading": "Garageport",
                                "text": "4x4,5 m"
                            },
                            {
                                "heading": "Dörr",
                                "text": "Ståldörr typ Daloc"
                            },
                            {
                                "heading": "Trappor",
                                "text": "Spiraltrappa i stål"
                            }
                        ]
                    },
                    {
                        "heading": "Installationer",
                        "characteristics": [
                            {
                                "heading": "VVS",
                                "text": "Fastigheten ansluts till kommunala nätet"
                            },
                            {
                                "heading": "Uppvärmning",
                                "text": "Frånluftvärmepump med golvvärme"
                            },
                            {
                                "heading": "TV/Tele/Bredband",
                                "text": "Fastigheten är förberedd för att anslutas till fibernät"
                            },
                            {
                                "heading": "Ventilation",
                                "text": "Mekanisk till- och frånluftsvent. Varje enskild bostadsrättshavare svarar för att ventilationen är dimensionerad efter sin verksamhet"
                            }
                        ]
                    }
                ],
                "pictures": [
                    {
                        "fileName": "hfp08-01.png"
                    },
                    {
                        "fileName": "hfp08-02.png"
                    }
                ],
                "thumbnail": "standardenhet.png",
                "googleMapsUrl": "https://www.google.com/maps/embed?pb=!1m18!1m12!1m3!1d1702.582084811809!2d21.02675231660073!3d64.7415872728741!2m3!1f0!2f0!3f0!3m2!1i1024!2i768!4f13.1!3m3!1m2!1s0x0%3A0x0!2zNjTCsDQ0JzI5LjciTiAyMcKwMDEnNDQuMiJF!5e0!3m2!1ssv!2sse!4v1527750055465",
                "size": 144,
                "price": 1229000,
                "rent": 4360,
                "sold": false
            },
            {
                "id": "hfp09",
                "projectId": "hedensbyn",
                "salesAgent": {
                    "id": "1989fb0b-15c0-4034-9e1c-2b8004e6e1c0",
                    "name": "Jörgen Munter",
                    "email": "jorgen.munter@industriradhus.se",
                    "phone": "070-173 37 88",
                    "picture": {
                        "fileName": "jorgen.png"
                    }
                },
                "name": "Standardenhet (HFP09)",
                "mainDescription": {
                    "id": "1009",
                    "heading": "Standardenhet",
                    "text": "HFP09",
                    "size": 1
                },
                "descriptions": null,
                "characteristicsSections": [
                    {
                        "heading": "Byggnadsbeskrivning",
                        "characteristics": [
                            {
                                "heading": "Grund",
                                "text": "Isolerad betongplatta"
                            },
                            {
                                "heading": "Fasad",
                                "text": "Plåt"
                            },
                            {
                                "heading": "Stomme",
                                "text": "Stål"
                            },
                            {
                                "heading": "Yttertak",
                                "text": "Takpapp"
                            },
                            {
                                "heading": "Innertak",
                                "text": "Takplåt"
                            },
                            {
                                "heading": "Fönster",
                                "text": "3-glas"
                            },
                            {
                                "heading": "Garageport",
                                "text": "4x4,5 m"
                            },
                            {
                                "heading": "Dörr",
                                "text": "Ståldörr typ Daloc"
                            },
                            {
                                "heading": "Trappor",
                                "text": "Spiraltrappa i stål"
                            }
                        ]
                    },
                    {
                        "heading": "Installationer",
                        "characteristics": [
                            {
                                "heading": "VVS",
                                "text": "Fastigheten ansluts till kommunala nätet"
                            },
                            {
                                "heading": "Uppvärmning",
                                "text": "Frånluftvärmepump med golvvärme"
                            },
                            {
                                "heading": "TV/Tele/Bredband",
                                "text": "Fastigheten är förberedd för att anslutas till fibernät"
                            },
                            {
                                "heading": "Ventilation",
                                "text": "Mekanisk till- och frånluftsvent. Varje enskild bostadsrättshavare svarar för att ventilationen är dimensionerad efter sin verksamhet"
                            }
                        ]
                    }
                ],
                "pictures": [
                    {
                        "fileName": "hfp09-01.png"
                    },
                    {
                        "fileName": "hfp09-02.png"
                    }
                ],
                "thumbnail": "standardenhet.png",
                "googleMapsUrl": "https://www.google.com/maps/embed?pb=!1m18!1m12!1m3!1d1702.582084811809!2d21.02675231660073!3d64.7415872728741!2m3!1f0!2f0!3f0!3m2!1i1024!2i768!4f13.1!3m3!1m2!1s0x0%3A0x0!2zNjTCsDQ0JzI5LjciTiAyMcKwMDEnNDQuMiJF!5e0!3m2!1ssv!2sse!4v1527750055465",
                "size": 144,
                "price": 1229000,
                "rent": 4360,
                "sold": false
            },
            {
                "id": "hfp10",
                "projectId": "hedensbyn",
                "salesAgent": {
                    "id": "1989fb0b-15c0-4034-9e1c-2b8004e6e1c0",
                    "name": "Jörgen Munter",
                    "email": "jorgen.munter@industriradhus.se",
                    "phone": "070-173 37 88",
                    "picture": {
                        "fileName": "jorgen.png"
                    }
                },
                "name": "Standardenhet (HFP10)",
                "mainDescription": {
                    "id": "1010",
                    "heading": "Standardenhet",
                    "text": "HFP10",
                    "size": 1
                },
                "descriptions": null,
                "characteristicsSections": [
                    {
                        "heading": "Byggnadsbeskrivning",
                        "characteristics": [
                            {
                                "heading": "Grund",
                                "text": "Isolerad betongplatta"
                            },
                            {
                                "heading": "Fasad",
                                "text": "Plåt"
                            },
                            {
                                "heading": "Stomme",
                                "text": "Stål"
                            },
                            {
                                "heading": "Yttertak",
                                "text": "Takpapp"
                            },
                            {
                                "heading": "Innertak",
                                "text": "Takplåt"
                            },
                            {
                                "heading": "Fönster",
                                "text": "3-glas"
                            },
                            {
                                "heading": "Garageport",
                                "text": "4x4,5 m"
                            },
                            {
                                "heading": "Dörr",
                                "text": "Ståldörr typ Daloc"
                            },
                            {
                                "heading": "Trappor",
                                "text": "Spiraltrappa i stål"
                            }
                        ]
                    },
                    {
                        "heading": "Installationer",
                        "characteristics": [
                            {
                                "heading": "VVS",
                                "text": "Fastigheten ansluts till kommunala nätet"
                            },
                            {
                                "heading": "Uppvärmning",
                                "text": "Frånluftvärmepump med golvvärme"
                            },
                            {
                                "heading": "TV/Tele/Bredband",
                                "text": "Fastigheten är förberedd för att anslutas till fibernät"
                            },
                            {
                                "heading": "Ventilation",
                                "text": "Mekanisk till- och frånluftsvent. Varje enskild bostadsrättshavare svarar för att ventilationen är dimensionerad efter sin verksamhet"
                            }
                        ]
                    }
                ],
                "pictures": [
                    {
                        "fileName": "hfp10-01.png"
                    },
                    {
                        "fileName": "hfp10-02.png"
                    }
                ],
                "thumbnail": "standardenhet.png",
                "googleMapsUrl": "https://www.google.com/maps/embed?pb=!1m18!1m12!1m3!1d1702.582084811809!2d21.02675231660073!3d64.7415872728741!2m3!1f0!2f0!3f0!3m2!1i1024!2i768!4f13.1!3m3!1m2!1s0x0%3A0x0!2zNjTCsDQ0JzI5LjciTiAyMcKwMDEnNDQuMiJF!5e0!3m2!1ssv!2sse!4v1527750055465",
                "size": 144,
                "price": 1229000,
                "rent": 4360,
                "sold": false
            },
            {
                "id": "hfp11",
                "projectId": "hedensbyn",
                "salesAgent": {
                    "id": "1989fb0b-15c0-4034-9e1c-2b8004e6e1c0",
                    "name": "Jörgen Munter",
                    "email": "jorgen.munter@industriradhus.se",
                    "phone": "070-173 37 88",
                    "picture": {
                        "fileName": "jorgen.png"
                    }
                },
                "name": "Standardenhet (HFP11)",
                "mainDescription": {
                    "id": "1011",
                    "heading": "Standardenhet",
                    "text": "HFP11",
                    "size": 1
                },
                "descriptions": null,
                "characteristicsSections": [
                    {
                        "heading": "Byggnadsbeskrivning",
                        "characteristics": [
                            {
                                "heading": "Grund",
                                "text": "Isolerad betongplatta"
                            },
                            {
                                "heading": "Fasad",
                                "text": "Plåt"
                            },
                            {
                                "heading": "Stomme",
                                "text": "Stål"
                            },
                            {
                                "heading": "Yttertak",
                                "text": "Takpapp"
                            },
                            {
                                "heading": "Innertak",
                                "text": "Takplåt"
                            },
                            {
                                "heading": "Fönster",
                                "text": "3-glas"
                            },
                            {
                                "heading": "Garageport",
                                "text": "4x4,5 m"
                            },
                            {
                                "heading": "Dörr",
                                "text": "Ståldörr typ Daloc"
                            },
                            {
                                "heading": "Trappor",
                                "text": "Spiraltrappa i stål"
                            }
                        ]
                    },
                    {
                        "heading": "Installationer",
                        "characteristics": [
                            {
                                "heading": "VVS",
                                "text": "Fastigheten ansluts till kommunala nätet"
                            },
                            {
                                "heading": "Uppvärmning",
                                "text": "Frånluftvärmepump med golvvärme"
                            },
                            {
                                "heading": "TV/Tele/Bredband",
                                "text": "Fastigheten är förberedd för att anslutas till fibernät"
                            },
                            {
                                "heading": "Ventilation",
                                "text": "Mekanisk till- och frånluftsvent. Varje enskild bostadsrättshavare svarar för att ventilationen är dimensionerad efter sin verksamhet"
                            }
                        ]
                    }
                ],
                "pictures": [
                    {
                        "fileName": "hfp11-01.png"
                    },
                    {
                        "fileName": "hfp11-02.png"
                    }
                ],
                "thumbnail": "standardenhet.png",
                "googleMapsUrl": "https://www.google.com/maps/embed?pb=!1m18!1m12!1m3!1d1702.582084811809!2d21.02675231660073!3d64.7415872728741!2m3!1f0!2f0!3f0!3m2!1i1024!2i768!4f13.1!3m3!1m2!1s0x0%3A0x0!2zNjTCsDQ0JzI5LjciTiAyMcKwMDEnNDQuMiJF!5e0!3m2!1ssv!2sse!4v1527750055465",
                "size": 144,
                "price": 1229000,
                "rent": 4360,
                "sold": false
            },
            {
                "id": "hfp12",
                "projectId": "hedensbyn",
                "salesAgent": {
                    "id": "1989fb0b-15c0-4034-9e1c-2b8004e6e1c0",
                    "name": "Jörgen Munter",
                    "email": "jorgen.munter@industriradhus.se",
                    "phone": "070-173 37 88",
                    "picture": {
                        "fileName": "jorgen.png"
                    }
                },
                "name": "Dubbelenhet (HFP12)",
                "mainDescription": {
                    "id": "1012",
                    "heading": "Dubbelenhet",
                    "text": "HFP12",
                    "size": 1
                },
                "descriptions": null,
                "characteristicsSections": [
                    {
                        "heading": "Byggnadsbeskrivning",
                        "characteristics": [
                            {
                                "heading": "Grund",
                                "text": "Isolerad betongplatta"
                            },
                            {
                                "heading": "Fasad",
                                "text": "Plåt"
                            },
                            {
                                "heading": "Stomme",
                                "text": "Stål"
                            },
                            {
                                "heading": "Yttertak",
                                "text": "Takpapp"
                            },
                            {
                                "heading": "Innertak",
                                "text": "Takplåt"
                            },
                            {
                                "heading": "Fönster",
                                "text": "3-glas"
                            },
                            {
                                "heading": "Garageport",
                                "text": "4x4,5 m"
                            },
                            {
                                "heading": "Dörr",
                                "text": "Ståldörr typ Daloc"
                            },
                            {
                                "heading": "Trappor",
                                "text": "Spiraltrappa i stål"
                            }
                        ]
                    },
                    {
                        "heading": "Installationer",
                        "characteristics": [
                            {
                                "heading": "VVS",
                                "text": "Fastigheten ansluts till kommunala nätet"
                            },
                            {
                                "heading": "Uppvärmning",
                                "text": "Frånluftvärmepump med golvvärme"
                            },
                            {
                                "heading": "TV/Tele/Bredband",
                                "text": "Fastigheten är förberedd för att anslutas till fibernät"
                            },
                            {
                                "heading": "Ventilation",
                                "text": "Mekanisk till- och frånluftsvent. Varje enskild bostadsrättshavare svarar för att ventilationen är dimensionerad efter sin verksamhet"
                            }
                        ]
                    }
                ],
                "pictures": [
                    {
                        "fileName": "hfp12-01.png"
                    },
                    {
                        "fileName": "hfp12-02.png"
                    }
                ],
                "thumbnail": "dubbelenhet.png",
                "googleMapsUrl": "https://www.google.com/maps/embed?pb=!1m18!1m12!1m3!1d1702.582084811809!2d21.02675231660073!3d64.7415872728741!2m3!1f0!2f0!3f0!3m2!1i1024!2i768!4f13.1!3m3!1m2!1s0x0%3A0x0!2zNjTCsDQ0JzI5LjciTiAyMcKwMDEnNDQuMiJF!5e0!3m2!1ssv!2sse!4v1527750055465",
                "size": 288,
                "price": 2459000,
                "rent": 8720,
                "sold": false
            },
            {
                "id": "hfp13",
                "projectId": "hedensbyn",
                "salesAgent": {
                    "id": "1989fb0b-15c0-4034-9e1c-2b8004e6e1c0",
                    "name": "Jörgen Munter",
                    "email": "jorgen.munter@industriradhus.se",
                    "phone": "070-173 37 88",
                    "picture": {
                        "fileName": "jorgen.png"
                    }
                },
                "name": "Dubbelenhet (HFP13)",
                "mainDescription": {
                    "id": "1013",
                    "heading": "Dubbelenhet",
                    "text": "HFP13",
                    "size": 1
                },
                "descriptions": null,
                "characteristicsSections": [
                    {
                        "heading": "Byggnadsbeskrivning",
                        "characteristics": [
                            {
                                "heading": "Grund",
                                "text": "Isolerad betongplatta"
                            },
                            {
                                "heading": "Fasad",
                                "text": "Plåt"
                            },
                            {
                                "heading": "Stomme",
                                "text": "Stål"
                            },
                            {
                                "heading": "Yttertak",
                                "text": "Takpapp"
                            },
                            {
                                "heading": "Innertak",
                                "text": "Takplåt"
                            },
                            {
                                "heading": "Fönster",
                                "text": "3-glas"
                            },
                            {
                                "heading": "Garageport",
                                "text": "4x4,5 m"
                            },
                            {
                                "heading": "Dörr",
                                "text": "Ståldörr typ Daloc"
                            },
                            {
                                "heading": "Trappor",
                                "text": "Spiraltrappa i stål"
                            }
                        ]
                    },
                    {
                        "heading": "Installationer",
                        "characteristics": [
                            {
                                "heading": "VVS",
                                "text": "Fastigheten ansluts till kommunala nätet"
                            },
                            {
                                "heading": "Uppvärmning",
                                "text": "Frånluftvärmepump med golvvärme"
                            },
                            {
                                "heading": "TV/Tele/Bredband",
                                "text": "Fastigheten är förberedd för att anslutas till fibernät"
                            },
                            {
                                "heading": "Ventilation",
                                "text": "Mekanisk till- och frånluftsvent. Varje enskild bostadsrättshavare svarar för att ventilationen är dimensionerad efter sin verksamhet"
                            }
                        ]
                    }
                ],
                "pictures": [
                    {
                        "fileName": "hfp13-01.png"
                    },
                    {
                        "fileName": "hfp13-02.png"
                    }
                ],
                "thumbnail": "dubbelenhet.png",
                "googleMapsUrl": "https://www.google.com/maps/embed?pb=!1m18!1m12!1m3!1d1702.582084811809!2d21.02675231660073!3d64.7415872728741!2m3!1f0!2f0!3f0!3m2!1i1024!2i768!4f13.1!3m3!1m2!1s0x0%3A0x0!2zNjTCsDQ0JzI5LjciTiAyMcKwMDEnNDQuMiJF!5e0!3m2!1ssv!2sse!4v1527750055465",
                "size": 288,
                "price": 2459000,
                "rent": 8720,
                "sold": false
            },
            {
                "id": "hfp14",
                "projectId": "hedensbyn",
                "salesAgent": {
                    "id": "1989fb0b-15c0-4034-9e1c-2b8004e6e1c0",
                    "name": "Jörgen Munter",
                    "email": "jorgen.munter@industriradhus.se",
                    "phone": "070-173 37 88",
                    "picture": {
                        "fileName": "jorgen.png"
                    }
                },
                "name": "Dubbelenhet (HFP14)",
                "mainDescription": {
                    "id": "1014",
                    "heading": "Dubbelenhet",
                    "text": "HFP14",
                    "size": 1
                },
                "descriptions": null,
                "characteristicsSections": [
                    {
                        "heading": "Byggnadsbeskrivning",
                        "characteristics": [
                            {
                                "heading": "Grund",
                                "text": "Isolerad betongplatta"
                            },
                            {
                                "heading": "Fasad",
                                "text": "Plåt"
                            },
                            {
                                "heading": "Stomme",
                                "text": "Stål"
                            },
                            {
                                "heading": "Yttertak",
                                "text": "Takpapp"
                            },
                            {
                                "heading": "Innertak",
                                "text": "Takplåt"
                            },
                            {
                                "heading": "Fönster",
                                "text": "3-glas"
                            },
                            {
                                "heading": "Garageport",
                                "text": "4x4,5 m"
                            },
                            {
                                "heading": "Dörr",
                                "text": "Ståldörr typ Daloc"
                            },
                            {
                                "heading": "Trappor",
                                "text": "Spiraltrappa i stål"
                            }
                        ]
                    },
                    {
                        "heading": "Installationer",
                        "characteristics": [
                            {
                                "heading": "VVS",
                                "text": "Fastigheten ansluts till kommunala nätet"
                            },
                            {
                                "heading": "Uppvärmning",
                                "text": "Frånluftvärmepump med golvvärme"
                            },
                            {
                                "heading": "TV/Tele/Bredband",
                                "text": "Fastigheten är förberedd för att anslutas till fibernät"
                            },
                            {
                                "heading": "Ventilation",
                                "text": "Mekanisk till- och frånluftsvent. Varje enskild bostadsrättshavare svarar för att ventilationen är dimensionerad efter sin verksamhet"
                            }
                        ]
                    }
                ],
                "pictures": [
                    {
                        "fileName": "hfp14-01.png"
                    },
                    {
                        "fileName": "hfp14-02.png"
                    }
                ],
                "thumbnail": "dubbelenhet.png",
                "googleMapsUrl": "https://www.google.com/maps/embed?pb=!1m18!1m12!1m3!1d1702.582084811809!2d21.02675231660073!3d64.7415872728741!2m3!1f0!2f0!3f0!3m2!1i1024!2i768!4f13.1!3m3!1m2!1s0x0%3A0x0!2zNjTCsDQ0JzI5LjciTiAyMcKwMDEnNDQuMiJF!5e0!3m2!1ssv!2sse!4v1527750055465",
                "size": 288,
                "price": 2459000,
                "rent": 8720,
                "sold": false
            },
            {
                "id": "hfp15",
                "projectId": "hedensbyn",
                "salesAgent": {
                    "id": "1989fb0b-15c0-4034-9e1c-2b8004e6e1c0",
                    "name": "Jörgen Munter",
                    "email": "jorgen.munter@industriradhus.se",
                    "phone": "070-173 37 88",
                    "picture": {
                        "fileName": "jorgen.png"
                    }
                },
                "name": "Dubbelenhet (HFP15)",
                "mainDescription": {
                    "id": "1015",
                    "heading": "Dubbelenhet",
                    "text": "HFP15",
                    "size": 1
                },
                "descriptions": null,
                "characteristicsSections": [
                    {
                        "heading": "Byggnadsbeskrivning",
                        "characteristics": [
                            {
                                "heading": "Grund",
                                "text": "Isolerad betongplatta"
                            },
                            {
                                "heading": "Fasad",
                                "text": "Plåt"
                            },
                            {
                                "heading": "Stomme",
                                "text": "Stål"
                            },
                            {
                                "heading": "Yttertak",
                                "text": "Takpapp"
                            },
                            {
                                "heading": "Innertak",
                                "text": "Takplåt"
                            },
                            {
                                "heading": "Fönster",
                                "text": "3-glas"
                            },
                            {
                                "heading": "Garageport",
                                "text": "4x4,5 m"
                            },
                            {
                                "heading": "Dörr",
                                "text": "Ståldörr typ Daloc"
                            },
                            {
                                "heading": "Trappor",
                                "text": "Spiraltrappa i stål"
                            }
                        ]
                    },
                    {
                        "heading": "Installationer",
                        "characteristics": [
                            {
                                "heading": "VVS",
                                "text": "Fastigheten ansluts till kommunala nätet"
                            },
                            {
                                "heading": "Uppvärmning",
                                "text": "Frånluftvärmepump med golvvärme"
                            },
                            {
                                "heading": "TV/Tele/Bredband",
                                "text": "Fastigheten är förberedd för att anslutas till fibernät"
                            },
                            {
                                "heading": "Ventilation",
                                "text": "Mekanisk till- och frånluftsvent. Varje enskild bostadsrättshavare svarar för att ventilationen är dimensionerad efter sin verksamhet"
                            }
                        ]
                    }
                ],
                "pictures": [
                    {
                        "fileName": "hfp15-01.png"
                    },
                    {
                        "fileName": "hfp15-02.png"
                    }
                ],
                "thumbnail": "dubbelenhet.png",
                "googleMapsUrl": "https://www.google.com/maps/embed?pb=!1m18!1m12!1m3!1d1702.582084811809!2d21.02675231660073!3d64.7415872728741!2m3!1f0!2f0!3f0!3m2!1i1024!2i768!4f13.1!3m3!1m2!1s0x0%3A0x0!2zNjTCsDQ0JzI5LjciTiAyMcKwMDEnNDQuMiJF!5e0!3m2!1ssv!2sse!4v1527750055465",
                "size": 288,
                "price": 2459000,
                "rent": 8720,
                "sold": false
            },
            {
                "id": "hfp16",
                "projectId": "hedensbyn",
                "salesAgent": {
                    "id": "1989fb0b-15c0-4034-9e1c-2b8004e6e1c0",
                    "name": "Jörgen Munter",
                    "email": "jorgen.munter@industriradhus.se",
                    "phone": "070-173 37 88",
                    "picture": {
                        "fileName": "jorgen.png"
                    }
                },
                "name": "Kontor (HFP16)",
                "mainDescription": {
                    "id": "1016",
                    "heading": "Kontor",
                    "text": "HFP16",
                    "size": 1
                },
                "descriptions": null,
                "characteristicsSections": [
                    {
                        "heading": "Byggnadsbeskrivning",
                        "characteristics": [
                            {
                                "heading": "Grund",
                                "text": "Isolerad betongplatta"
                            },
                            {
                                "heading": "Fasad",
                                "text": "Plåt"
                            },
                            {
                                "heading": "Stomme",
                                "text": "Stål"
                            },
                            {
                                "heading": "Yttertak",
                                "text": "Takpapp"
                            },
                            {
                                "heading": "Innertak",
                                "text": "Takplåt"
                            },
                            {
                                "heading": "Fönster",
                                "text": "3-glas"
                            },
                            {
                                "heading": "Garageport",
                                "text": "4x4,5 m"
                            },
                            {
                                "heading": "Dörr",
                                "text": "Ståldörr typ Daloc"
                            },
                            {
                                "heading": "Trappor",
                                "text": "Spiraltrappa i stål"
                            }
                        ]
                    },
                    {
                        "heading": "Installationer",
                        "characteristics": [
                            {
                                "heading": "VVS",
                                "text": "Fastigheten ansluts till kommunala nätet"
                            },
                            {
                                "heading": "Uppvärmning",
                                "text": "Frånluftvärmepump med golvvärme"
                            },
                            {
                                "heading": "TV/Tele/Bredband",
                                "text": "Fastigheten är förberedd för att anslutas till fibernät"
                            },
                            {
                                "heading": "Ventilation",
                                "text": "Mekanisk till- och frånluftsvent. Varje enskild bostadsrättshavare svarar för att ventilationen är dimensionerad efter sin verksamhet"
                            }
                        ]
                    }
                ],
                "pictures": [
                    {
                        "fileName": "hfp16-01.png"
                    },
                    {
                        "fileName": "hfp16-02.png"
                    }
                ],
                "thumbnail": "kontor.png",
                "googleMapsUrl": "https://www.google.com/maps/embed?pb=!1m18!1m12!1m3!1d1702.582084811809!2d21.02675231660073!3d64.7415872728741!2m3!1f0!2f0!3f0!3m2!1i1024!2i768!4f13.1!3m3!1m2!1s0x0%3A0x0!2zNjTCsDQ0JzI5LjciTiAyMcKwMDEnNDQuMiJF!5e0!3m2!1ssv!2sse!4v1527750055465",
                "size": 233,
                "price": 3459000,
                "rent": 8720,
                "sold": false
            },
            {
                "id": "hfp17",
                "projectId": "hedensbyn",
                "salesAgent": {
                    "id": "1989fb0b-15c0-4034-9e1c-2b8004e6e1c0",
                    "name": "Jörgen Munter",
                    "email": "jorgen.munter@industriradhus.se",
                    "phone": "070-173 37 88",
                    "picture": {
                        "fileName": "jorgen.png"
                    }
                },
                "name": "Kontor (HFP17)",
                "mainDescription": {
                    "id": "1017",
                    "heading": "Kontor",
                    "text": "HFP17",
                    "size": 1
                },
                "descriptions": null,
                "characteristicsSections": [
                    {
                        "heading": "Byggnadsbeskrivning",
                        "characteristics": [
                            {
                                "heading": "Grund",
                                "text": "Isolerad betongplatta"
                            },
                            {
                                "heading": "Fasad",
                                "text": "Plåt"
                            },
                            {
                                "heading": "Stomme",
                                "text": "Stål"
                            },
                            {
                                "heading": "Yttertak",
                                "text": "Takpapp"
                            },
                            {
                                "heading": "Innertak",
                                "text": "Takplåt"
                            },
                            {
                                "heading": "Fönster",
                                "text": "3-glas"
                            },
                            {
                                "heading": "Garageport",
                                "text": "4x4,5 m"
                            },
                            {
                                "heading": "Dörr",
                                "text": "Ståldörr typ Daloc"
                            },
                            {
                                "heading": "Trappor",
                                "text": "Spiraltrappa i stål"
                            }
                        ]
                    },
                    {
                        "heading": "Installationer",
                        "characteristics": [
                            {
                                "heading": "VVS",
                                "text": "Fastigheten ansluts till kommunala nätet"
                            },
                            {
                                "heading": "Uppvärmning",
                                "text": "Frånluftvärmepump med golvvärme"
                            },
                            {
                                "heading": "TV/Tele/Bredband",
                                "text": "Fastigheten är förberedd för att anslutas till fibernät"
                            },
                            {
                                "heading": "Ventilation",
                                "text": "Mekanisk till- och frånluftsvent. Varje enskild bostadsrättshavare svarar för att ventilationen är dimensionerad efter sin verksamhet"
                            }
                        ]
                    }
                ],
                "pictures": [
                    {
                        "fileName": "hfp17-01.png"
                    },
                    {
                        "fileName": "hfp17-02.png"
                    }
                ],
                "thumbnail": "kontor.png",
                "googleMapsUrl": "https://www.google.com/maps/embed?pb=!1m18!1m12!1m3!1d1702.582084811809!2d21.02675231660073!3d64.7415872728741!2m3!1f0!2f0!3f0!3m2!1i1024!2i768!4f13.1!3m3!1m2!1s0x0%3A0x0!2zNjTCsDQ0JzI5LjciTiAyMcKwMDEnNDQuMiJF!5e0!3m2!1ssv!2sse!4v1527750055465",
                "size": 233,
                "price": 3459000,
                "rent": 8720,
                "sold": false
            },
            {
                "id": "hfp18",
                "projectId": "hedensbyn",
                "salesAgent": {
                    "id": "1989fb0b-15c0-4034-9e1c-2b8004e6e1c0",
                    "name": "Jörgen Munter",
                    "email": "jorgen.munter@industriradhus.se",
                    "phone": "070-173 37 88",
                    "picture": {
                        "fileName": "jorgen.png"
                    }
                },
                "name": "Kontor med garage (HFP18)",
                "mainDescription": {
                    "id": "1018",
                    "heading": "Kontor med garage",
                    "text": "HFP18",
                    "size": 1
                },
                "descriptions": null,
                "characteristicsSections": [
                    {
                        "heading": "Byggnadsbeskrivning",
                        "characteristics": [
                            {
                                "heading": "Grund",
                                "text": "Isolerad betongplatta"
                            },
                            {
                                "heading": "Fasad",
                                "text": "Plåt"
                            },
                            {
                                "heading": "Stomme",
                                "text": "Stål"
                            },
                            {
                                "heading": "Yttertak",
                                "text": "Takpapp"
                            },
                            {
                                "heading": "Innertak",
                                "text": "Takplåt"
                            },
                            {
                                "heading": "Fönster",
                                "text": "3-glas"
                            },
                            {
                                "heading": "Garageport",
                                "text": "4x4,5 m"
                            },
                            {
                                "heading": "Dörr",
                                "text": "Ståldörr typ Daloc"
                            },
                            {
                                "heading": "Trappor",
                                "text": "Spiraltrappa i stål"
                            }
                        ]
                    },
                    {
                        "heading": "Installationer",
                        "characteristics": [
                            {
                                "heading": "VVS",
                                "text": "Fastigheten ansluts till kommunala nätet"
                            },
                            {
                                "heading": "Uppvärmning",
                                "text": "Frånluftvärmepump med golvvärme"
                            },
                            {
                                "heading": "TV/Tele/Bredband",
                                "text": "Fastigheten är förberedd för att anslutas till fibernät"
                            },
                            {
                                "heading": "Ventilation",
                                "text": "Mekanisk till- och frånluftsvent. Varje enskild bostadsrättshavare svarar för att ventilationen är dimensionerad efter sin verksamhet"
                            }
                        ]
                    }
                ],
                "pictures": [
                    {
                        "fileName": "hfp18-01.png"
                    },
                    {
                        "fileName": "hfp18-02.png"
                    }
                ],
                "thumbnail": "kontor-med-garage.png",
                "googleMapsUrl": "https://www.google.com/maps/embed?pb=!1m18!1m12!1m3!1d1702.582084811809!2d21.02675231660073!3d64.7415872728741!2m3!1f0!2f0!3f0!3m2!1i1024!2i768!4f13.1!3m3!1m2!1s0x0%3A0x0!2zNjTCsDQ0JzI5LjciTiAyMcKwMDEnNDQuMiJF!5e0!3m2!1ssv!2sse!4v1527750055465",
                "size": 377,
                "price": 5919000,
                "rent": 17440,
                "sold": false
            },
            {
                "id": "hfp19",
                "projectId": "hedensbyn",
                "salesAgent": {
                    "id": "1989fb0b-15c0-4034-9e1c-2b8004e6e1c0",
                    "name": "Jörgen Munter",
                    "email": "jorgen.munter@industriradhus.se",
                    "phone": "070-173 37 88",
                    "picture": {
                        "fileName": "jorgen.png"
                    }
                },
                "name": "Kontor med garage (HFP19)",
                "mainDescription": {
                    "id": "1019",
                    "heading": "Kontor med garage",
                    "text": "HFP19",
                    "size": 1
                },
                "descriptions": null,
                "characteristicsSections": [
                    {
                        "heading": "Byggnadsbeskrivning",
                        "characteristics": [
                            {
                                "heading": "Grund",
                                "text": "Isolerad betongplatta"
                            },
                            {
                                "heading": "Fasad",
                                "text": "Plåt"
                            },
                            {
                                "heading": "Stomme",
                                "text": "Stål"
                            },
                            {
                                "heading": "Yttertak",
                                "text": "Takpapp"
                            },
                            {
                                "heading": "Innertak",
                                "text": "Takplåt"
                            },
                            {
                                "heading": "Fönster",
                                "text": "3-glas"
                            },
                            {
                                "heading": "Garageport",
                                "text": "4x4,5 m"
                            },
                            {
                                "heading": "Dörr",
                                "text": "Ståldörr typ Daloc"
                            },
                            {
                                "heading": "Trappor",
                                "text": "Spiraltrappa i stål"
                            }
                        ]
                    },
                    {
                        "heading": "Installationer",
                        "characteristics": [
                            {
                                "heading": "VVS",
                                "text": "Fastigheten ansluts till kommunala nätet"
                            },
                            {
                                "heading": "Uppvärmning",
                                "text": "Frånluftvärmepump med golvvärme"
                            },
                            {
                                "heading": "TV/Tele/Bredband",
                                "text": "Fastigheten är förberedd för att anslutas till fibernät"
                            },
                            {
                                "heading": "Ventilation",
                                "text": "Mekanisk till- och frånluftsvent. Varje enskild bostadsrättshavare svarar för att ventilationen är dimensionerad efter sin verksamhet"
                            }
                        ]
                    }
                ],
                "pictures": [
                    {
                        "fileName": "hfp19-01.png"
                    },
                    {
                        "fileName": "hfp19-02.png"
                    }
                ],
                "thumbnail": "kontor-med-garage.png",
                "googleMapsUrl": "https://www.google.com/maps/embed?pb=!1m18!1m12!1m3!1d1702.582084811809!2d21.02675231660073!3d64.7415872728741!2m3!1f0!2f0!3f0!3m2!1i1024!2i768!4f13.1!3m3!1m2!1s0x0%3A0x0!2zNjTCsDQ0JzI5LjciTiAyMcKwMDEnNDQuMiJF!5e0!3m2!1ssv!2sse!4v1527750055465",
                "size": 377,
                "price": 5919000,
                "rent": 17440,
                "sold": false
            },
            {
                "id": "hfp20",
                "projectId": "hedensbyn",
                "salesAgent": {
                    "id": "1989fb0b-15c0-4034-9e1c-2b8004e6e1c0",
                    "name": "Jörgen Munter",
                    "email": "jorgen.munter@industriradhus.se",
                    "phone": "070-173 37 88",
                    "picture": {
                        "fileName": "jorgen.png"
                    }
                },
                "name": "Butik (HFP20)",
                "mainDescription": {
                    "id": "1020",
                    "heading": "Butik",
                    "text": "HFP20",
                    "size": 1
                },
                "descriptions": null,
                "characteristicsSections": [
                    {
                        "heading": "Byggnadsbeskrivning",
                        "characteristics": [
                            {
                                "heading": "Grund",
                                "text": "Isolerad betongplatta"
                            },
                            {
                                "heading": "Fasad",
                                "text": "Plåt"
                            },
                            {
                                "heading": "Stomme",
                                "text": "Stål"
                            },
                            {
                                "heading": "Yttertak",
                                "text": "Takpapp"
                            },
                            {
                                "heading": "Innertak",
                                "text": "Takplåt"
                            },
                            {
                                "heading": "Fönster",
                                "text": "3-glas"
                            },
                            {
                                "heading": "Garageport",
                                "text": "4x4,5 m"
                            },
                            {
                                "heading": "Dörr",
                                "text": "Ståldörr typ Daloc"
                            },
                            {
                                "heading": "Trappor",
                                "text": "Spiraltrappa i stål"
                            }
                        ]
                    },
                    {
                        "heading": "Installationer",
                        "characteristics": [
                            {
                                "heading": "VVS",
                                "text": "Fastigheten ansluts till kommunala nätet"
                            },
                            {
                                "heading": "Uppvärmning",
                                "text": "Frånluftvärmepump med golvvärme"
                            },
                            {
                                "heading": "TV/Tele/Bredband",
                                "text": "Fastigheten är förberedd för att anslutas till fibernät"
                            },
                            {
                                "heading": "Ventilation",
                                "text": "Mekanisk till- och frånluftsvent. Varje enskild bostadsrättshavare svarar för att ventilationen är dimensionerad efter sin verksamhet"
                            }
                        ]
                    }
                ],
                "pictures": [
                    {
                        "fileName": "hfp20-01.png"
                    },
                    {
                        "fileName": "hfp20-02.png"
                    }
                ],
                "thumbnail": "butik.png",
                "googleMapsUrl": "https://www.google.com/maps/embed?pb=!1m18!1m12!1m3!1d1702.582084811809!2d21.02675231660073!3d64.7415872728741!2m3!1f0!2f0!3f0!3m2!1i1024!2i768!4f13.1!3m3!1m2!1s0x0%3A0x0!2zNjTCsDQ0JzI5LjciTiAyMcKwMDEnNDQuMiJF!5e0!3m2!1ssv!2sse!4v1527750055465",
                "size": 330,
                "price": 5919000,
                "rent": 17440,
                "sold": false
            },
            {
                "id": "hfp21",
                "projectId": "hedensbyn",
                "salesAgent": {
                    "id": "1989fb0b-15c0-4034-9e1c-2b8004e6e1c0",
                    "name": "Jörgen Munter",
                    "email": "jorgen.munter@industriradhus.se",
                    "phone": "070-173 37 88",
                    "picture": {
                        "fileName": "jorgen.png"
                    }
                },
                "name": "Butik (HFP21)",
                "mainDescription": {
                    "id": "1020",
                    "heading": "Butik",
                    "text": "HFP21",
                    "size": 1
                },
                "descriptions": null,
                "characteristicsSections": [
                    {
                        "heading": "Byggnadsbeskrivning",
                        "characteristics": [
                            {
                                "heading": "Grund",
                                "text": "Isolerad betongplatta"
                            },
                            {
                                "heading": "Fasad",
                                "text": "Plåt"
                            },
                            {
                                "heading": "Stomme",
                                "text": "Stål"
                            },
                            {
                                "heading": "Yttertak",
                                "text": "Takpapp"
                            },
                            {
                                "heading": "Innertak",
                                "text": "Takplåt"
                            },
                            {
                                "heading": "Fönster",
                                "text": "3-glas"
                            },
                            {
                                "heading": "Garageport",
                                "text": "4x4,5 m"
                            },
                            {
                                "heading": "Dörr",
                                "text": "Ståldörr typ Daloc"
                            },
                            {
                                "heading": "Trappor",
                                "text": "Spiraltrappa i stål"
                            }
                        ]
                    },
                    {
                        "heading": "Installationer",
                        "characteristics": [
                            {
                                "heading": "VVS",
                                "text": "Fastigheten ansluts till kommunala nätet"
                            },
                            {
                                "heading": "Uppvärmning",
                                "text": "Frånluftvärmepump med golvvärme"
                            },
                            {
                                "heading": "TV/Tele/Bredband",
                                "text": "Fastigheten är förberedd för att anslutas till fibernät"
                            },
                            {
                                "heading": "Ventilation",
                                "text": "Mekanisk till- och frånluftsvent. Varje enskild bostadsrättshavare svarar för att ventilationen är dimensionerad efter sin verksamhet"
                            }
                        ]
                    }
                ],
                "pictures": [
                    {
                        "fileName": "hfp21-01.png"
                    },
                    {
                        "fileName": "hfp21-02.png"
                    }
                ],
                "thumbnail": "butik.png",
                "googleMapsUrl": "https://www.google.com/maps/embed?pb=!1m18!1m12!1m3!1d1702.582084811809!2d21.02675231660073!3d64.7415872728741!2m3!1f0!2f0!3f0!3m2!1i1024!2i768!4f13.1!3m3!1m2!1s0x0%3A0x0!2zNjTCsDQ0JzI5LjciTiAyMcKwMDEnNDQuMiJF!5e0!3m2!1ssv!2sse!4v1527750055465",
                "size": 330,
                "price": 5919000,
                "rent": 17440,
                "sold": false
            }
        ]
    }
]